linkml_runtime/__init__.py
linkml_runtime/dumpers/__init__.py
linkml_runtime/dumpers/csv_dumper.py
linkml_runtime/dumpers/delimited_file_dumper.py
linkml_runtime/dumpers/dumper_root.py
linkml_runtime/dumpers/json_dumper.py
linkml_runtime/dumpers/rdf_dumper.py
linkml_runtime/dumpers/rdflib_dumper.py
linkml_runtime/dumpers/tsv_dumper.py
linkml_runtime/dumpers/yaml_dumper.py
linkml_runtime/exceptions.py
linkml_runtime/index/__init__.py
linkml_runtime/index/object_index.py
linkml_runtime/linkml_model/README.md
linkml_runtime/linkml_model/__init__.py
linkml_runtime/linkml_model/annotations.py
linkml_runtime/linkml_model/array.py
linkml_runtime/linkml_model/datasets.py
linkml_runtime/linkml_model/excel/meta.xlsx
linkml_runtime/linkml_model/extensions.py
linkml_runtime/linkml_model/graphql/README.md
linkml_runtime/linkml_model/graphql/meta.graphql
linkml_runtime/linkml_model/json/README.md
linkml_runtime/linkml_model/json/annotations.json
linkml_runtime/linkml_model/json/datasets.json
linkml_runtime/linkml_model/json/extensions.json
linkml_runtime/linkml_model/json/mappings.json
linkml_runtime/linkml_model/json/meta.json
linkml_runtime/linkml_model/json/types.json
linkml_runtime/linkml_model/json/units.json
linkml_runtime/linkml_model/json/validation.json
linkml_runtime/linkml_model/jsonld/README.md
linkml_runtime/linkml_model/jsonld/annotations.context.jsonld
linkml_runtime/linkml_model/jsonld/annotations.model.context.jsonld
linkml_runtime/linkml_model/jsonld/context.jsonld
linkml_runtime/linkml_model/jsonld/datasets.context.jsonld
linkml_runtime/linkml_model/jsonld/datasets.model.context.jsonld
linkml_runtime/linkml_model/jsonld/extensions.context.jsonld
linkml_runtime/linkml_model/jsonld/extensions.model.context.jsonld
linkml_runtime/linkml_model/jsonld/mappings.context.jsonld
linkml_runtime/linkml_model/jsonld/mappings.model.context.jsonld
linkml_runtime/linkml_model/jsonld/meta.context.jsonld
linkml_runtime/linkml_model/jsonld/meta.jsonld
linkml_runtime-1.9.5.dist-info/LICENSE
linkml_runtime-1.9.5.dist-info/METADATA
linkml_runtime-1.9.5.dist-info/WHEEL
linkml_runtime-1.9.5.dist-info/entry_points.txt
linkml_runtime-1.9.5.dist-info/RECORD
