Metadata-Version: 2.3
Name: linkml-runtime
Version: 1.9.5
Summary: Runtime environment for LinkML, the Linked open data modeling language
License: CC0-1.0
Keywords: linkml,metamodel,schema visualization,rdf,owl,yaml
Author: Chris Mungall
Author-email: cjmungall@lbl.gov
Requires-Python: >=3.9
Classifier: Development Status :: 5 - Production/Stable
Classifier: Environment :: Console
Classifier: Intended Audience :: Developers
Classifier: Intended Audience :: Science/Research
Classifier: Intended Audience :: Healthcare Industry
Classifier: Topic :: Software Development :: Libraries :: Python Modules
Classifier: Programming Language :: Python :: 3.9
Classifier: Programming Language :: Python :: 3.10
Classifier: Programming Language :: Python :: 3.11
Classifier: Programming Language :: Python :: 3.12
Classifier: Programming Language :: Python :: 3.13
Requires-Dist: click
Requires-Dist: curies (>=0.5.4)
Requires-Dist: deprecated
Requires-Dist: hbreader
Requires-Dist: isodate (>=0.7.2,<1.0.0) ; python_version < "3.11"
Requires-Dist: json-flattener (>=0.1.9)
Requires-Dist: jsonasobj2 (>=1.0.4,<2.dev0)
Requires-Dist: jsonschema (>=3.2.0)
Requires-Dist: prefixcommons (>=0.1.12)
Requires-Dist: prefixmaps (>=0.1.4)
Requires-Dist: pydantic (>=1.10.2,<3.0.0)
Requires-Dist: pyyaml
Requires-Dist: rdflib (>=6.0.0)
Requires-Dist: requests
